pdf2sqlite/__init__.py
pdf2sqlite/__main__.py
pdf2sqlite/abstract.py
pdf2sqlite/describe_figure.py
pdf2sqlite/embeddings.py
pdf2sqlite/extract_sections.py
pdf2sqlite/init_db.py
pdf2sqlite/pdf2sqlite.py
pdf2sqlite/pdf_to_table.py
pdf2sqlite/streaming.py
pdf2sqlite/summarize.py
pdf2sqlite/task_stack.py
pdf2sqlite/validation.py
pdf2sqlite/view.py
pdf2sqlite/mcp_server/__init__.py
pdf2sqlite/mcp_server/__main__.py
pdf2sqlite/mcp_server/config.py
pdf2sqlite/mcp_server/db.py
pdf2sqlite/mcp_server/resources.py
pdf2sqlite/mcp_server/server.py
pdf2sqlite/mcp_server/tools.py
pdf2sqlite/mcp_server/uri.py
pdf2sqlite/sql/create_db.sql
pdf2sqlite-0.0.3.dist-info/METADATA
pdf2sqlite-0.0.3.dist-info/WHEEL
pdf2sqlite-0.0.3.dist-info/entry_points.txt
pdf2sqlite-0.0.3.dist-info/licenses/LICENSE
pdf2sqlite-0.0.3.dist-info/RECORD
