Metadata-Version: 2.4
Name: pdf2sqlite
Version: 0.0.3
Summary: Builds a searchable sqlite knowledge base out of pdf data
Project-URL: Homepage, https://github.com/draperlaboratory/pdf2sqlite
Project-URL: Issues, https://github.com/draperlaboratory/pdf2sqlite/issues
Maintainer-email: Graham Leach-Krouse <gleach-krouse@draper.com>
License-Expression: MIT
License-File: LICENSE
Requires-Python: >=3.12
Requires-Dist: boto3
Requires-Dist: gmft
Requires-Dist: litellm
Requires-Dist: mcp>=0.4.1
Requires-Dist: numpy
Requires-Dist: pypdf==6.0.0
Requires-Dist: rich
Requires-Dist: rich-argparse>=1.7.1
Requires-Dist: scikit-learn
Requires-Dist: sqlite-vec
